{
  "symbol": "CEKA",
  "ticker": "CEKA.JK",
  "fetched_at": "2026-04-22T12:11:26.495166",
  "trading_days": 56,
  "market_score": 55,
  "context": {
    "last_close": 2310.0,
    "sma20": 2271.5,
    "sma50": 2314.6,
    "ema20": 2294.22,
    "above_sma20": true,
    "above_sma50": false,
    "rsi_14": 51.95,
    "macd": {
      "macd": 1.4446,
      "signal": -7.6183,
      "histogram": 9.0628,
      "trend": "BULLISH"
    },
    "volume": {
      "avg_60d": 29998,
      "avg_7d": 12514,
      "last": 4500,
      "ratio_7d": 0.42,
      "ratio_1d": 0.15,
      "trend": "CONTRACTING",
      "spike_today": false
    },
    "momentum": {
      "return_5d": 0.87,
      "return_20d": 5.0,
      "return_60d": -5.33,
      "trend": "MIXED"
    },
    "high_60d": 2500.0,
    "low_60d": 2180.0,
    "pct_from_high": -7.6,
    "pct_from_low": 5.96,
    "market_score": 55
  },
  "ohlcv": [
    {
      "date": "2026-01-22",
      "open": 2490.0,
      "high": 2500.0,
      "low": 2430.0,
      "close": 2440.0,
      "volume": 10300
    },
    {
      "date": "2026-01-23",
      "open": 2500.0,
      "high": 2500.0,
      "low": 2440.0,
      "close": 2470.0,
      "volume": 17200
    },
    {
      "date": "2026-01-26",
      "open": 2500.0,
      "high": 2500.0,
      "low": 2420.0,
      "close": 2440.0,
      "volume": 9800
    },
    {
      "date": "2026-01-27",
      "open": 2500.0,
      "high": 2500.0,
      "low": 2440.0,
      "close": 2480.0,
      "volume": 24900
    },
    {
      "date": "2026-01-28",
      "open": 2480.0,
      "high": 2480.0,
      "low": 2400.0,
      "close": 2400.0,
      "volume": 42800
    },
    {
      "date": "2026-01-29",
      "open": 2400.0,
      "high": 2400.0,
      "low": 2300.0,
      "close": 2310.0,
      "volume": 92800
    },
    {
      "date": "2026-01-30",
      "open": 2350.0,
      "high": 2500.0,
      "low": 2300.0,
      "close": 2300.0,
      "volume": 66000
    },
    {
      "date": "2026-02-02",
      "open": 2310.0,
      "high": 2360.0,
      "low": 2300.0,
      "close": 2300.0,
      "volume": 64900
    },
    {
      "date": "2026-02-03",
      "open": 2300.0,
      "high": 2370.0,
      "low": 2300.0,
      "close": 2330.0,
      "volume": 22600
    },
    {
      "date": "2026-02-04",
      "open": 2360.0,
      "high": 2390.0,
      "low": 2340.0,
      "close": 2360.0,
      "volume": 16000
    },
    {
      "date": "2026-02-05",
      "open": 2360.0,
      "high": 2370.0,
      "low": 2360.0,
      "close": 2360.0,
      "volume": 11800
    },
    {
      "date": "2026-02-06",
      "open": 2360.0,
      "high": 2370.0,
      "low": 2340.0,
      "close": 2350.0,
      "volume": 5400
    },
    {
      "date": "2026-02-09",
      "open": 2360.0,
      "high": 2360.0,
      "low": 2300.0,
      "close": 2340.0,
      "volume": 29600
    },
    {
      "date": "2026-02-10",
      "open": 2340.0,
      "high": 2400.0,
      "low": 2330.0,
      "close": 2330.0,
      "volume": 15300
    },
    {
      "date": "2026-02-11",
      "open": 2350.0,
      "high": 2350.0,
      "low": 2330.0,
      "close": 2350.0,
      "volume": 14000
    },
    {
      "date": "2026-02-12",
      "open": 2360.0,
      "high": 2370.0,
      "low": 2330.0,
      "close": 2360.0,
      "volume": 15400
    },
    {
      "date": "2026-02-13",
      "open": 2360.0,
      "high": 2360.0,
      "low": 2330.0,
      "close": 2360.0,
      "volume": 20000
    },
    {
      "date": "2026-02-18",
      "open": 2360.0,
      "high": 2390.0,
      "low": 2340.0,
      "close": 2390.0,
      "volume": 23000
    },
    {
      "date": "2026-02-19",
      "open": 2470.0,
      "high": 2470.0,
      "low": 2350.0,
      "close": 2410.0,
      "volume": 8700
    },
    {
      "date": "2026-02-20",
      "open": 2410.0,
      "high": 2410.0,
      "low": 2360.0,
      "close": 2410.0,
      "volume": 24300
    },
    {
      "date": "2026-02-23",
      "open": 2420.0,
      "high": 2420.0,
      "low": 2400.0,
      "close": 2400.0,
      "volume": 29600
    },
    {
      "date": "2026-02-24",
      "open": 2410.0,
      "high": 2420.0,
      "low": 2390.0,
      "close": 2400.0,
      "volume": 26800
    },
    {
      "date": "2026-02-25",
      "open": 2400.0,
      "high": 2410.0,
      "low": 2390.0,
      "close": 2390.0,
      "volume": 7200
    },
    {
      "date": "2026-02-26",
      "open": 2390.0,
      "high": 2390.0,
      "low": 2370.0,
      "close": 2370.0,
      "volume": 8000
    },
    {
      "date": "2026-02-27",
      "open": 2370.0,
      "high": 2450.0,
      "low": 2370.0,
      "close": 2400.0,
      "volume": 8700
    },
    {
      "date": "2026-03-02",
      "open": 2400.0,
      "high": 2400.0,
      "low": 2360.0,
      "close": 2370.0,
      "volume": 33300
    },
    {
      "date": "2026-03-03",
      "open": 2370.0,
      "high": 2380.0,
      "low": 2320.0,
      "close": 2350.0,
      "volume": 29200
    },
    {
      "date": "2026-03-04",
      "open": 2350.0,
      "high": 2350.0,
      "low": 2220.0,
      "close": 2320.0,
      "volume": 65500
    },
    {
      "date": "2026-03-05",
      "open": 2320.0,
      "high": 2380.0,
      "low": 2290.0,
      "close": 2330.0,
      "volume": 3300
    },
    {
      "date": "2026-03-06",
      "open": 2350.0,
      "high": 2350.0,
      "low": 2290.0,
      "close": 2350.0,
      "volume": 14500
    },
    {
      "date": "2026-03-09",
      "open": 2350.0,
      "high": 2450.0,
      "low": 2190.0,
      "close": 2380.0,
      "volume": 193900
    },
    {
      "date": "2026-03-10",
      "open": 2360.0,
      "high": 2370.0,
      "low": 2210.0,
      "close": 2370.0,
      "volume": 26100
    },
    {
      "date": "2026-03-11",
      "open": 2370.0,
      "high": 2370.0,
      "low": 2240.0,
      "close": 2250.0,
      "volume": 168600
    },
    {
      "date": "2026-03-12",
      "open": 2250.0,
      "high": 2280.0,
      "low": 2240.0,
      "close": 2250.0,
      "volume": 8700
    },
    {
      "date": "2026-03-13",
      "open": 2240.0,
      "high": 2240.0,
      "low": 2200.0,
      "close": 2220.0,
      "volume": 22500
    },
    {
      "date": "2026-03-16",
      "open": 2220.0,
      "high": 2220.0,
      "low": 2180.0,
      "close": 2200.0,
      "volume": 40800
    },
    {
      "date": "2026-03-17",
      "open": 2210.0,
      "high": 2240.0,
      "low": 2200.0,
      "close": 2200.0,
      "volume": 27400
    },
    {
      "date": "2026-03-25",
      "open": 2230.0,
      "high": 2250.0,
      "low": 2200.0,
      "close": 2200.0,
      "volume": 20600
    },
    {
      "date": "2026-03-26",
      "open": 2200.0,
      "high": 2300.0,
      "low": 2200.0,
      "close": 2200.0,
      "volume": 38700
    },
    {
      "date": "2026-03-27",
      "open": 2210.0,
      "high": 2260.0,
      "low": 2190.0,
      "close": 2250.0,
      "volume": 205300
    },
    {
      "date": "2026-03-30",
      "open": 2260.0,
      "high": 2280.0,
      "low": 2200.0,
      "close": 2250.0,
      "volume": 6200
    },
    {
      "date": "2026-03-31",
      "open": 2220.0,
      "high": 2350.0,
      "low": 2220.0,
      "close": 2240.0,
      "volume": 10500
    },
    {
      "date": "2026-04-01",
      "open": 2350.0,
      "high": 2350.0,
      "low": 2250.0,
      "close": 2250.0,
      "volume": 4800
    },
    {
      "date": "2026-04-02",
      "open": 2250.0,
      "high": 2310.0,
      "low": 2250.0,
      "close": 2290.0,
      "volume": 3900
    },
    {
      "date": "2026-04-06",
      "open": 2290.0,
      "high": 2370.0,
      "low": 2240.0,
      "close": 2240.0,
      "volume": 16700
    },
    {
      "date": "2026-04-07",
      "open": 2310.0,
      "high": 2340.0,
      "low": 2270.0,
      "close": 2280.0,
      "volume": 4600
    },
    {
      "date": "2026-04-08",
      "open": 2290.0,
      "high": 2290.0,
      "low": 2210.0,
      "close": 2290.0,
      "volume": 24200
    },
    {
      "date": "2026-04-09",
      "open": 2300.0,
      "high": 2300.0,
      "low": 2250.0,
      "close": 2290.0,
      "volume": 5200
    },
    {
      "date": "2026-04-10",
      "open": 2300.0,
      "high": 2330.0,
      "low": 2260.0,
      "close": 2300.0,
      "volume": 2700
    },
    {
      "date": "2026-04-13",
      "open": 2300.0,
      "high": 2300.0,
      "low": 2280.0,
      "close": 2280.0,
      "volume": 7000
    },
    {
      "date": "2026-04-14",
      "open": 2310.0,
      "high": 2330.0,
      "low": 2290.0,
      "close": 2290.0,
      "volume": 22100
    },
    {
      "date": "2026-04-15",
      "open": 2330.0,
      "high": 2340.0,
      "low": 2280.0,
      "close": 2340.0,
      "volume": 13400
    },
    {
      "date": "2026-04-16",
      "open": 2310.0,
      "high": 2340.0,
      "low": 2300.0,
      "close": 2300.0,
      "volume": 9500
    },
    {
      "date": "2026-04-17",
      "open": 2320.0,
      "high": 2330.0,
      "low": 2310.0,
      "close": 2320.0,
      "volume": 7600
    },
    {
      "date": "2026-04-20",
      "open": 2330.0,
      "high": 2350.0,
      "low": 2280.0,
      "close": 2310.0,
      "volume": 23500
    },
    {
      "date": "2026-04-21",
      "open": 2310.0,
      "high": 2310.0,
      "low": 2300.0,
      "close": 2310.0,
      "volume": 4500
    }
  ]
}