{
  "symbol": "MEGA",
  "ticker": "MEGA.JK",
  "fetched_at": "2026-04-22T12:12:06.410761",
  "trading_days": 56,
  "market_score": 40,
  "context": {
    "last_close": 2630.0,
    "sma20": 2453.97,
    "sma50": 2087.5,
    "ema20": 2497.35,
    "above_sma20": true,
    "above_sma50": true,
    "rsi_14": 58.86,
    "macd": {
      "macd": 198.8776,
      "signal": 200.0805,
      "histogram": -1.2029,
      "trend": "BEARISH"
    },
    "volume": {
      "avg_60d": 528862,
      "avg_7d": 325971,
      "last": 79800,
      "ratio_7d": 0.62,
      "ratio_1d": 0.15,
      "trend": "CONTRACTING",
      "spike_today": false
    },
    "momentum": {
      "return_5d": -6.07,
      "return_20d": 34.79,
      "return_60d": 62.55,
      "trend": "MIXED"
    },
    "high_60d": 3100.0,
    "low_60d": 1521.37,
    "pct_from_high": -15.16,
    "pct_from_low": 72.87,
    "market_score": 40
  },
  "ohlcv": [
    {
      "date": "2026-01-22",
      "open": 1613.14,
      "high": 1627.63,
      "low": 1613.14,
      "close": 1617.97,
      "volume": 31600
    },
    {
      "date": "2026-01-23",
      "open": 1642.12,
      "high": 1646.95,
      "low": 1608.31,
      "close": 1608.31,
      "volume": 49400
    },
    {
      "date": "2026-01-26",
      "open": 1613.14,
      "high": 1632.46,
      "low": 1608.31,
      "close": 1627.63,
      "volume": 52200
    },
    {
      "date": "2026-01-27",
      "open": 1627.63,
      "high": 1637.29,
      "low": 1617.97,
      "close": 1627.63,
      "volume": 42800
    },
    {
      "date": "2026-01-28",
      "open": 1622.8,
      "high": 1622.8,
      "low": 1574.5,
      "close": 1593.82,
      "volume": 70400
    },
    {
      "date": "2026-01-29",
      "open": 1593.82,
      "high": 1593.82,
      "low": 1521.37,
      "close": 1593.82,
      "volume": 38400
    },
    {
      "date": "2026-01-30",
      "open": 1598.65,
      "high": 1632.46,
      "low": 1584.16,
      "close": 1588.99,
      "volume": 10400
    },
    {
      "date": "2026-02-02",
      "open": 1588.99,
      "high": 1637.29,
      "low": 1579.33,
      "close": 1579.33,
      "volume": 36600
    },
    {
      "date": "2026-02-03",
      "open": 1579.33,
      "high": 1584.16,
      "low": 1569.67,
      "close": 1579.33,
      "volume": 10000
    },
    {
      "date": "2026-02-04",
      "open": 1613.14,
      "high": 1613.14,
      "low": 1579.33,
      "close": 1593.82,
      "volume": 2000
    },
    {
      "date": "2026-02-05",
      "open": 1593.82,
      "high": 1608.31,
      "low": 1564.84,
      "close": 1593.82,
      "volume": 29800
    },
    {
      "date": "2026-02-06",
      "open": 1593.82,
      "high": 1593.82,
      "low": 1569.67,
      "close": 1569.67,
      "volume": 33800
    },
    {
      "date": "2026-02-09",
      "open": 1569.67,
      "high": 1593.82,
      "low": 1569.67,
      "close": 1593.82,
      "volume": 2200
    },
    {
      "date": "2026-02-10",
      "open": 1593.82,
      "high": 1593.82,
      "low": 1593.82,
      "close": 1593.82,
      "volume": 4200
    },
    {
      "date": "2026-02-11",
      "open": 1617.97,
      "high": 1627.63,
      "low": 1598.65,
      "close": 1603.48,
      "volume": 77200
    },
    {
      "date": "2026-02-12",
      "open": 1617.97,
      "high": 1637.29,
      "low": 1593.82,
      "close": 1613.14,
      "volume": 15600
    },
    {
      "date": "2026-02-13",
      "open": 1608.31,
      "high": 1608.31,
      "low": 1569.67,
      "close": 1603.48,
      "volume": 29600
    },
    {
      "date": "2026-02-18",
      "open": 1608.31,
      "high": 1608.31,
      "low": 1584.16,
      "close": 1588.99,
      "volume": 20000
    },
    {
      "date": "2026-02-19",
      "open": 1598.65,
      "high": 1598.65,
      "low": 1574.5,
      "close": 1579.33,
      "volume": 12600
    },
    {
      "date": "2026-02-20",
      "open": 1579.33,
      "high": 1617.97,
      "low": 1579.33,
      "close": 1598.65,
      "volume": 15000
    },
    {
      "date": "2026-02-23",
      "open": 1738.71,
      "high": 1994.69,
      "low": 1738.71,
      "close": 1994.69,
      "volume": 668600
    },
    {
      "date": "2026-02-24",
      "open": 2487.32,
      "high": 2487.32,
      "low": 2487.32,
      "close": 2487.32,
      "volume": 1612600
    },
    {
      "date": "2026-02-25",
      "open": 2897.85,
      "high": 2982.37,
      "low": 2236.18,
      "close": 2337.6,
      "volume": 6547000
    },
    {
      "date": "2026-02-26",
      "open": 2337.6,
      "high": 2680.51,
      "low": 2337.6,
      "close": 2347.26,
      "volume": 972400
    },
    {
      "date": "2026-02-27",
      "open": 2356.92,
      "high": 2366.58,
      "low": 2245.84,
      "close": 2245.84,
      "volume": 306800
    },
    {
      "date": "2026-03-02",
      "open": 2216.86,
      "high": 2216.86,
      "low": 2052.65,
      "close": 2086.45,
      "volume": 434000
    },
    {
      "date": "2026-03-03",
      "open": 2086.45,
      "high": 2173.39,
      "low": 2004.35,
      "close": 2071.96,
      "volume": 199600
    },
    {
      "date": "2026-03-04",
      "open": 2052.65,
      "high": 2057.48,
      "low": 1888.43,
      "close": 1931.9,
      "volume": 314600
    },
    {
      "date": "2026-03-05",
      "open": 1931.9,
      "high": 1999.52,
      "low": 1931.9,
      "close": 1946.39,
      "volume": 80800
    },
    {
      "date": "2026-03-06",
      "open": 1946.39,
      "high": 1946.39,
      "low": 1883.6,
      "close": 1941.56,
      "volume": 162600
    },
    {
      "date": "2026-03-09",
      "open": 1941.56,
      "high": 1941.56,
      "low": 1762.86,
      "close": 1873.94,
      "volume": 157800
    },
    {
      "date": "2026-03-10",
      "open": 1898.09,
      "high": 1999.52,
      "low": 1898.09,
      "close": 1956.05,
      "volume": 71600
    },
    {
      "date": "2026-03-11",
      "open": 1970.54,
      "high": 2004.35,
      "low": 1956.05,
      "close": 1956.05,
      "volume": 98400
    },
    {
      "date": "2026-03-12",
      "open": 1956.05,
      "high": 2004.35,
      "low": 1936.73,
      "close": 1956.05,
      "volume": 60200
    },
    {
      "date": "2026-03-13",
      "open": 1956.05,
      "high": 1956.05,
      "low": 1922.24,
      "close": 1931.9,
      "volume": 79600
    },
    {
      "date": "2026-03-16",
      "open": 1931.9,
      "high": 1951.22,
      "low": 1907.75,
      "close": 1951.22,
      "volume": 81800
    },
    {
      "date": "2026-03-17",
      "open": 1946.39,
      "high": 1956.05,
      "low": 1931.9,
      "close": 1956.05,
      "volume": 30800
    },
    {
      "date": "2026-03-25",
      "open": 1956.05,
      "high": 2023.67,
      "low": 1931.9,
      "close": 2004.35,
      "volume": 125400
    },
    {
      "date": "2026-03-26",
      "open": 2009.18,
      "high": 2294.13,
      "low": 2009.18,
      "close": 2197.54,
      "volume": 401000
    },
    {
      "date": "2026-03-27",
      "open": 2245.84,
      "high": 2308.62,
      "low": 2197.54,
      "close": 2265.16,
      "volume": 231400
    },
    {
      "date": "2026-03-30",
      "open": 2265.16,
      "high": 2269.98,
      "low": 2110.6,
      "close": 2192.71,
      "volume": 130600
    },
    {
      "date": "2026-03-31",
      "open": 2260.33,
      "high": 2260.33,
      "low": 2173.39,
      "close": 2197.54,
      "volume": 198600
    },
    {
      "date": "2026-04-01",
      "open": 2221.69,
      "high": 2274.81,
      "low": 2038.16,
      "close": 2052.65,
      "volume": 629200
    },
    {
      "date": "2026-04-02",
      "open": 2139.58,
      "high": 2154.07,
      "low": 2014.01,
      "close": 2052.65,
      "volume": 125000
    },
    {
      "date": "2026-04-06",
      "open": 2173.39,
      "high": 2173.39,
      "low": 2071.96,
      "close": 2168.56,
      "volume": 664000
    },
    {
      "date": "2026-04-07",
      "open": 2221.69,
      "high": 2704.66,
      "low": 2173.39,
      "close": 2704.66,
      "volume": 4790800
    },
    {
      "date": "2026-04-08",
      "open": 2777.11,
      "high": 2922.0,
      "low": 2583.92,
      "close": 2668.44,
      "volume": 2768400
    },
    {
      "date": "2026-04-09",
      "open": 2668.44,
      "high": 2668.44,
      "low": 2414.88,
      "close": 2439.03,
      "volume": 2536400
    },
    {
      "date": "2026-04-10",
      "open": 2570.0,
      "high": 3100.0,
      "low": 2570.0,
      "close": 2950.0,
      "volume": 2270700
    },
    {
      "date": "2026-04-13",
      "open": 2900.0,
      "high": 2920.0,
      "low": 2760.0,
      "close": 2900.0,
      "volume": 475300
    },
    {
      "date": "2026-04-14",
      "open": 2910.0,
      "high": 2920.0,
      "low": 2800.0,
      "close": 2800.0,
      "volume": 646600
    },
    {
      "date": "2026-04-15",
      "open": 2850.0,
      "high": 2850.0,
      "low": 2730.0,
      "close": 2780.0,
      "volume": 484500
    },
    {
      "date": "2026-04-16",
      "open": 2790.0,
      "high": 2800.0,
      "low": 2690.0,
      "close": 2740.0,
      "volume": 230000
    },
    {
      "date": "2026-04-17",
      "open": 2760.0,
      "high": 2810.0,
      "low": 2720.0,
      "close": 2730.0,
      "volume": 95000
    },
    {
      "date": "2026-04-20",
      "open": 2720.0,
      "high": 2740.0,
      "low": 2620.0,
      "close": 2650.0,
      "volume": 270600
    },
    {
      "date": "2026-04-21",
      "open": 2650.0,
      "high": 2690.0,
      "low": 2600.0,
      "close": 2630.0,
      "volume": 79800
    }
  ]
}