{
  "symbol": "TKIM",
  "ticker": "TKIM.JK",
  "fetched_at": "2026-04-22T12:10:50.224786",
  "trading_days": 56,
  "market_score": 35,
  "context": {
    "last_close": 9025.0,
    "sma20": 9062.5,
    "sma50": 8616.0,
    "ema20": 9061.55,
    "above_sma20": false,
    "above_sma50": true,
    "rsi_14": 49.84,
    "macd": {
      "macd": 79.4347,
      "signal": 120.6927,
      "histogram": -41.258,
      "trend": "BEARISH"
    },
    "volume": {
      "avg_60d": 3680445,
      "avg_7d": 2776986,
      "last": 747100,
      "ratio_7d": 0.75,
      "ratio_1d": 0.2,
      "trend": "CONTRACTING",
      "spike_today": false
    },
    "momentum": {
      "return_5d": -4.5,
      "return_20d": 6.18,
      "return_60d": 9.06,
      "trend": "MIXED"
    },
    "high_60d": 11300.0,
    "low_60d": 6450.0,
    "pct_from_high": -20.13,
    "pct_from_low": 39.92,
    "market_score": 35
  },
  "ohlcv": [
    {
      "date": "2026-01-22",
      "open": 8100.0,
      "high": 8375.0,
      "low": 8025.0,
      "close": 8275.0,
      "volume": 4116200
    },
    {
      "date": "2026-01-23",
      "open": 8350.0,
      "high": 8375.0,
      "low": 8000.0,
      "close": 8100.0,
      "volume": 1916800
    },
    {
      "date": "2026-01-26",
      "open": 8100.0,
      "high": 8125.0,
      "low": 7950.0,
      "close": 8000.0,
      "volume": 1171100
    },
    {
      "date": "2026-01-27",
      "open": 8025.0,
      "high": 8150.0,
      "low": 7950.0,
      "close": 8125.0,
      "volume": 1067500
    },
    {
      "date": "2026-01-28",
      "open": 7900.0,
      "high": 7900.0,
      "low": 7300.0,
      "close": 7575.0,
      "volume": 5722000
    },
    {
      "date": "2026-01-29",
      "open": 7300.0,
      "high": 7425.0,
      "low": 6450.0,
      "close": 7200.0,
      "volume": 4219700
    },
    {
      "date": "2026-01-30",
      "open": 7400.0,
      "high": 7400.0,
      "low": 7125.0,
      "close": 7300.0,
      "volume": 1518400
    },
    {
      "date": "2026-02-02",
      "open": 7300.0,
      "high": 7300.0,
      "low": 6500.0,
      "close": 6600.0,
      "volume": 3367100
    },
    {
      "date": "2026-02-03",
      "open": 6625.0,
      "high": 6950.0,
      "low": 6575.0,
      "close": 6800.0,
      "volume": 2408500
    },
    {
      "date": "2026-02-04",
      "open": 6950.0,
      "high": 7000.0,
      "low": 6800.0,
      "close": 6850.0,
      "volume": 1234000
    },
    {
      "date": "2026-02-05",
      "open": 7100.0,
      "high": 7350.0,
      "low": 7075.0,
      "close": 7200.0,
      "volume": 2866000
    },
    {
      "date": "2026-02-06",
      "open": 7150.0,
      "high": 7150.0,
      "low": 6975.0,
      "close": 7025.0,
      "volume": 1184000
    },
    {
      "date": "2026-02-09",
      "open": 7200.0,
      "high": 7275.0,
      "low": 7100.0,
      "close": 7150.0,
      "volume": 1110600
    },
    {
      "date": "2026-02-10",
      "open": 7150.0,
      "high": 7225.0,
      "low": 7100.0,
      "close": 7175.0,
      "volume": 549800
    },
    {
      "date": "2026-02-11",
      "open": 7175.0,
      "high": 7300.0,
      "low": 6975.0,
      "close": 7250.0,
      "volume": 1777800
    },
    {
      "date": "2026-02-12",
      "open": 7300.0,
      "high": 7350.0,
      "low": 7250.0,
      "close": 7300.0,
      "volume": 1322500
    },
    {
      "date": "2026-02-13",
      "open": 7275.0,
      "high": 7425.0,
      "low": 7200.0,
      "close": 7275.0,
      "volume": 1663700
    },
    {
      "date": "2026-02-18",
      "open": 7300.0,
      "high": 7300.0,
      "low": 7150.0,
      "close": 7200.0,
      "volume": 1019200
    },
    {
      "date": "2026-02-19",
      "open": 7225.0,
      "high": 7475.0,
      "low": 7225.0,
      "close": 7400.0,
      "volume": 1776900
    },
    {
      "date": "2026-02-20",
      "open": 7450.0,
      "high": 7475.0,
      "low": 7200.0,
      "close": 7300.0,
      "volume": 1446400
    },
    {
      "date": "2026-02-23",
      "open": 7350.0,
      "high": 7650.0,
      "low": 7300.0,
      "close": 7525.0,
      "volume": 1492400
    },
    {
      "date": "2026-02-24",
      "open": 7600.0,
      "high": 7675.0,
      "low": 7475.0,
      "close": 7625.0,
      "volume": 1349100
    },
    {
      "date": "2026-02-25",
      "open": 7650.0,
      "high": 9150.0,
      "low": 7650.0,
      "close": 9150.0,
      "volume": 18450400
    },
    {
      "date": "2026-02-26",
      "open": 9250.0,
      "high": 10975.0,
      "low": 9050.0,
      "close": 10975.0,
      "volume": 33068100
    },
    {
      "date": "2026-02-27",
      "open": 10400.0,
      "high": 11125.0,
      "low": 10000.0,
      "close": 11000.0,
      "volume": 9868900
    },
    {
      "date": "2026-03-02",
      "open": 10350.0,
      "high": 11300.0,
      "low": 9900.0,
      "close": 11200.0,
      "volume": 9058200
    },
    {
      "date": "2026-03-03",
      "open": 11150.0,
      "high": 11150.0,
      "low": 10500.0,
      "close": 10550.0,
      "volume": 3245400
    },
    {
      "date": "2026-03-04",
      "open": 10300.0,
      "high": 10300.0,
      "low": 9200.0,
      "close": 9375.0,
      "volume": 8903000
    },
    {
      "date": "2026-03-05",
      "open": 10100.0,
      "high": 10350.0,
      "low": 9850.0,
      "close": 10025.0,
      "volume": 8419400
    },
    {
      "date": "2026-03-06",
      "open": 9975.0,
      "high": 9975.0,
      "low": 9275.0,
      "close": 9275.0,
      "volume": 4209600
    },
    {
      "date": "2026-03-09",
      "open": 8575.0,
      "high": 8925.0,
      "low": 8150.0,
      "close": 8725.0,
      "volume": 6475100
    },
    {
      "date": "2026-03-10",
      "open": 9200.0,
      "high": 9625.0,
      "low": 8850.0,
      "close": 9550.0,
      "volume": 5636000
    },
    {
      "date": "2026-03-11",
      "open": 9500.0,
      "high": 9800.0,
      "low": 8925.0,
      "close": 8925.0,
      "volume": 2464800
    },
    {
      "date": "2026-03-12",
      "open": 8875.0,
      "high": 9125.0,
      "low": 8625.0,
      "close": 8725.0,
      "volume": 1701100
    },
    {
      "date": "2026-03-13",
      "open": 8625.0,
      "high": 8975.0,
      "low": 8375.0,
      "close": 8600.0,
      "volume": 2367100
    },
    {
      "date": "2026-03-16",
      "open": 8600.0,
      "high": 8600.0,
      "low": 8150.0,
      "close": 8500.0,
      "volume": 1537200
    },
    {
      "date": "2026-03-17",
      "open": 8700.0,
      "high": 9125.0,
      "low": 8700.0,
      "close": 9050.0,
      "volume": 2605500
    },
    {
      "date": "2026-03-25",
      "open": 8825.0,
      "high": 9350.0,
      "low": 8600.0,
      "close": 9300.0,
      "volume": 2809700
    },
    {
      "date": "2026-03-26",
      "open": 9375.0,
      "high": 9400.0,
      "low": 9075.0,
      "close": 9075.0,
      "volume": 2241100
    },
    {
      "date": "2026-03-27",
      "open": 9075.0,
      "high": 9300.0,
      "low": 8825.0,
      "close": 8850.0,
      "volume": 1197700
    },
    {
      "date": "2026-03-30",
      "open": 8700.0,
      "high": 9275.0,
      "low": 8575.0,
      "close": 9050.0,
      "volume": 2138900
    },
    {
      "date": "2026-03-31",
      "open": 9050.0,
      "high": 9350.0,
      "low": 8800.0,
      "close": 8900.0,
      "volume": 2183900
    },
    {
      "date": "2026-04-01",
      "open": 9500.0,
      "high": 9600.0,
      "low": 8875.0,
      "close": 8900.0,
      "volume": 2884300
    },
    {
      "date": "2026-04-02",
      "open": 8850.0,
      "high": 8850.0,
      "low": 8400.0,
      "close": 8400.0,
      "volume": 3181800
    },
    {
      "date": "2026-04-06",
      "open": 8375.0,
      "high": 8825.0,
      "low": 8350.0,
      "close": 8600.0,
      "volume": 1264600
    },
    {
      "date": "2026-04-07",
      "open": 8650.0,
      "high": 8975.0,
      "low": 8500.0,
      "close": 8825.0,
      "volume": 1370600
    },
    {
      "date": "2026-04-08",
      "open": 9000.0,
      "high": 9325.0,
      "low": 8900.0,
      "close": 9325.0,
      "volume": 2099800
    },
    {
      "date": "2026-04-09",
      "open": 9325.0,
      "high": 9350.0,
      "low": 9125.0,
      "close": 9300.0,
      "volume": 1401600
    },
    {
      "date": "2026-04-10",
      "open": 9375.0,
      "high": 9475.0,
      "low": 9150.0,
      "close": 9300.0,
      "volume": 1582500
    },
    {
      "date": "2026-04-13",
      "open": 9275.0,
      "high": 9650.0,
      "low": 8925.0,
      "close": 9650.0,
      "volume": 5817400
    },
    {
      "date": "2026-04-14",
      "open": 9700.0,
      "high": 10000.0,
      "low": 9425.0,
      "close": 9450.0,
      "volume": 3289500
    },
    {
      "date": "2026-04-15",
      "open": 9450.0,
      "high": 9700.0,
      "low": 9225.0,
      "close": 9300.0,
      "volume": 5129800
    },
    {
      "date": "2026-04-16",
      "open": 9325.0,
      "high": 9425.0,
      "low": 9100.0,
      "close": 9125.0,
      "volume": 1295000
    },
    {
      "date": "2026-04-17",
      "open": 9250.0,
      "high": 9275.0,
      "low": 8800.0,
      "close": 8875.0,
      "volume": 1903500
    },
    {
      "date": "2026-04-20",
      "open": 8925.0,
      "high": 9100.0,
      "low": 8850.0,
      "close": 8950.0,
      "volume": 1256600
    },
    {
      "date": "2026-04-21",
      "open": 8950.0,
      "high": 9100.0,
      "low": 8875.0,
      "close": 9025.0,
      "volume": 747100
    }
  ]
}